<?xml version="1.0" encoding="GB2312"?>
<!-- 配置文件  -->
<Config xmlns="http://dms/action"
	xmlns:xsi="http://www.w3.org/2001/XMLSchema-instance"
	xsi:schemaLocation="http://dms/action DefAction.xsd">
	
    <Action id="INIT_MODULE_ACTION">
        <Description></Description>
        <ActionContext>
            <Data name="MODULE_CODE" type="string"/>
            <Data name="MODULE" type="string" output="true"/>
        </ActionContext>
        <ActionParam>
            <ActionStep id="1" classname="cn.boho.framework.actions.BeginTransactionAction" on1Do="next" onOtherDo="3" />
            <ActionStep id="2" classname="com.hanthink.pub.action.InitModuleAction" on1Do="next" onOtherDo="3"/>
            <ActionStep id="3" classname="cn.boho.framework.actions.EndTransactionAction" onOtherDo="return" />
        </ActionParam>
    </Action>
    
    <Action id="QUERY_PUB_MODULE_ACTION">
        <Description>查询【模块表】</Description>
        <ActionContext>
            <Data name="PUB_MODULE" type="array" output="true"/>
        </ActionContext>
        <ActionParam>
            <ActionStep id="1" classname="cn.boho.framework.actions.BeginTransactionAction" on1Do="next" onOtherDo="3" />
            <ActionStep id="2" classname="com.hanthink.pub.action.QueryPubModuleAction" on1Do="next" onOtherDo="3"/>
            <ActionStep id="3" classname="cn.boho.framework.actions.EndTransactionAction" onOtherDo="return" />
        </ActionParam>
    </Action>
    
</Config>
